bcesigner.py
httpie_media_auth.py
mediaauth.py
httpie_media_auth-0.0.8.dist-info/DESCRIPTION.rst
httpie_media_auth-0.0.8.dist-info/METADATA
httpie_media_auth-0.0.8.dist-info/RECORD
httpie_media_auth-0.0.8.dist-info/WHEEL
httpie_media_auth-0.0.8.dist-info/entry_points.txt
httpie_media_auth-0.0.8.dist-info/metadata.json
httpie_media_auth-0.0.8.dist-info/top_level.txt
